vizmyip/__init__.py
vizmyip/app.py
vizmyip/templates/index.html
vizmyip-0.1.2.dist-info/LICENSE
vizmyip-0.1.2.dist-info/METADATA
vizmyip-0.1.2.dist-info/WHEEL
vizmyip-0.1.2.dist-info/entry_points.txt
vizmyip-0.1.2.dist-info/top_level.txt
vizmyip-0.1.2.dist-info/RECORD
