Metadata-Version: 2.1
Name: vizmyip
Version: 0.1.2
Summary: Visualizes public IP information of your system.
Home-page: https://github.com/asis2016/vizmyip
Author: Ashish S. Maharjan
Author-email: <hello@amaharjan.de>
License: MIT
Keywords: python,flask,ip,public ip
Platform: UNKNOWN
Classifier: Development Status :: 1 - Planning
Classifier: Intended Audience :: Developers
Classifier: Programming Language :: Python :: 3
Classifier: Operating System :: Unix
License-File: LICENSE
Requires-Dist: flask
Requires-Dist: requests
